django_user_email_extension/__init__.py
django_user_email_extension/admin.py
django_user_email_extension/apps.py
django_user_email_extension/forms.py
django_user_email_extension/languages.py
django_user_email_extension/models.py
django_user_email_extension/validators.py
django_user_email_extension/migrations/0001_initial.py
django_user_email_extension/migrations/0002_auto_20210814_1256.py
django_user_email_extension/migrations/__init__.py
django_user_email_extension/tests/__init__.py
django_user_email_extension/tests/settings.py
django_user_email_extension/tests/tests.py
django_user_email_extension-2.6.1.dist-info/LICENSE
django_user_email_extension-2.6.1.dist-info/METADATA
django_user_email_extension-2.6.1.dist-info/WHEEL
django_user_email_extension-2.6.1.dist-info/top_level.txt
django_user_email_extension-2.6.1.dist-info/RECORD
