Metadata-Version: 2.1
Name: django-user-email-extension
Version: 2.6.1
Summary: User model extender for django
Home-page: https://github.com/ArieLevs/Django-User-Email-Extension
Author: Arie Lev
Author-email: levinson.arie@gmail.com
Classifier: Programming Language :: Python :: 3
Classifier: Programming Language :: Python :: 3.10
Classifier: Programming Language :: Python :: 3.11
Classifier: Programming Language :: Python :: 3.12
Classifier: License :: OSI Approved :: Apache Software License
Classifier: Operating System :: OS Independent
Classifier: Framework :: Django
Classifier: Framework :: Django :: 4.0
Classifier: Framework :: Django :: 5.0
License-File: LICENSE
Requires-Dist: django>=5.0
Requires-Dist: django-countries==7.6.1
Requires-Dist: phonenumbers==8.13.45
Requires-Dist: django-phonenumber-field==8.0.0
Requires-Dist: pytz==2022.7.1
